{"version": "1", "message": "ERROR: Hidden Testcases server unreachable.", "problem_id": "ads2_m1_a1_1", "user_id": "PrasamsaNeelam", "score": {"sample": {"0": {"execution_time": 1.3486897945404053, "passed": true}, "1": {"execution_time": 0.25533342361450195, "passed": true}, "2": {"execution_time": 0.48072338104248047, "passed": false}, "3": {"execution_time": 0.28524041175842285, "passed": true}, "4": {"execution_time": 0.26818180084228516, "passed": true}, "5": {"execution_time": 0.5036799907684326, "passed": true}, "6": {"execution_time": 0.2351381778717041, "passed": true}, "7": {"execution_time": 0.3023679256439209, "passed": true}}}, "check_style_score": "0/1"}